poseigen_seaside/__init__.py
poseigen_seaside/basics.py
poseigen_seaside/metrics.py
poseigen_seaside/visuals.py
poseigen_seaside-0.1.0.dist-info/LICENSE.txt
poseigen_seaside-0.1.0.dist-info/METADATA
poseigen_seaside-0.1.0.dist-info/WHEEL
poseigen_seaside-0.1.0.dist-info/RECORD
